dash_improve_my_llms/__init__.py
dash_improve_my_llms/bot_detection.py
dash_improve_my_llms/html_generator.py
dash_improve_my_llms/py.typed
dash_improve_my_llms/robots_generator.py
dash_improve_my_llms/sitemap_generator.py
dash_improve_my_llms/toon_generator.py
dash_improve_my_llms-1.2.0.dist-info/licenses/LICENSE
dash_improve_my_llms-1.2.0.dist-info/METADATA
dash_improve_my_llms-1.2.0.dist-info/WHEEL
dash_improve_my_llms-1.2.0.dist-info/top_level.txt
dash_improve_my_llms-1.2.0.dist-info/RECORD
