Metadata-Version: 2.4
Name: dash-improve-my-llms
Version: 1.2.0
Summary: Automatic llms.txt, llms.toon (Token-Oriented Object Notation), page.json, architecture.txt, robots.txt, and sitemap.xml generation for Dash applications with comprehensive bot management, static HTML serving, and SEO optimization
Author-email: Pip Install Python LLC <pipinstallpython@gmail.com>
Maintainer-email: Pip Install Python LLC <pipinstallpython@gmail.com>
License-Expression: MIT
Project-URL: Homepage, https://pip-install-python.com
Project-URL: Documentation, https://github.com/pip-install-python/dash-improve-my-llms#readme
Project-URL: Repository, https://github.com/pip-install-python/dash-improve-my-llms
Project-URL: Bug Tracker, https://github.com/pip-install-python/dash-improve-my-llms/issues
Project-URL: Plotly Pro, https://plotly.pro
Keywords: dash,plotly,llms,ai,documentation,llms.txt,toon,token-oriented-object-notation,architecture,metadata,plugin,hook,bot-detection,robots-txt,sitemap,seo,analytics,visitor-tracking,web-crawlers,ai-bots
Classifier: Development Status :: 5 - Production/Stable
Classifier: Framework :: Dash
Classifier: Intended Audience :: Developers
Classifier: Operating System :: OS Independent
Classifier: Programming Language :: Python :: 3
Classifier: Programming Language :: Python :: 3.8
Classifier: Programming Language :: Python :: 3.9
Classifier: Programming Language :: Python :: 3.10
Classifier: Programming Language :: Python :: 3.11
Classifier: Programming Language :: Python :: 3.12
Classifier: Topic :: Documentation
Classifier: Topic :: Internet :: WWW/HTTP :: Dynamic Content
Classifier: Topic :: Software Development :: Libraries :: Python Modules
Classifier: Typing :: Typed
Requires-Python: >=3.8
License-File: LICENSE
Requires-Dist: dash>=3.0.0
Requires-Dist: flask>=2.0.0
Provides-Extra: dev
Requires-Dist: pytest>=7.0.0; extra == "dev"
Requires-Dist: pytest-cov>=4.0.0; extra == "dev"
Requires-Dist: black>=23.0.0; extra == "dev"
Requires-Dist: flake8>=6.0.0; extra == "dev"
Requires-Dist: mypy>=1.0.0; extra == "dev"
Requires-Dist: build>=0.10.0; extra == "dev"
Requires-Dist: twine>=4.0.0; extra == "dev"
Requires-Dist: dash-mantine-components>=2.0.0; extra == "dev"
Dynamic: license-file
